my_sensors/__init__.py
my_sensors/models.py
my_sensors/sensors/__init__.py
my_sensors/sensors/ccs811.py
my_sensors/sensors/dht22.py
my_sensors/sensors/tsl2561.py
my_sensors-0.1.0rc13.dist-info/LICENSE
my_sensors-0.1.0rc13.dist-info/WHEEL
my_sensors-0.1.0rc13.dist-info/METADATA
my_sensors-0.1.0rc13.dist-info/RECORD
